azure/mgmt/hardwaresecuritymodules/__init__.py
azure/mgmt/hardwaresecuritymodules/_client.py
azure/mgmt/hardwaresecuritymodules/_configuration.py
azure/mgmt/hardwaresecuritymodules/_patch.py
azure/mgmt/hardwaresecuritymodules/_version.py
azure/mgmt/hardwaresecuritymodules/py.typed
azure/mgmt/hardwaresecuritymodules/_utils/__init__.py
azure/mgmt/hardwaresecuritymodules/_utils/model_base.py
azure/mgmt/hardwaresecuritymodules/_utils/serialization.py
azure/mgmt/hardwaresecuritymodules/aio/__init__.py
azure/mgmt/hardwaresecuritymodules/aio/_client.py
azure/mgmt/hardwaresecuritymodules/aio/_configuration.py
azure/mgmt/hardwaresecuritymodules/aio/_patch.py
azure/mgmt/hardwaresecuritymodules/aio/operations/__init__.py
azure/mgmt/hardwaresecuritymodules/aio/operations/_operations.py
azure/mgmt/hardwaresecuritymodules/aio/operations/_patch.py
azure/mgmt/hardwaresecuritymodules/models/__init__.py
azure/mgmt/hardwaresecuritymodules/models/_enums.py
azure/mgmt/hardwaresecuritymodules/models/_models.py
azure/mgmt/hardwaresecuritymodules/models/_patch.py
azure/mgmt/hardwaresecuritymodules/operations/__init__.py
azure/mgmt/hardwaresecuritymodules/operations/_operations.py
azure/mgmt/hardwaresecuritymodules/operations/_patch.py
azure_mgmt_hardwaresecuritymodules-1.0.0.dist-info/LICENSE
azure_mgmt_hardwaresecuritymodules-1.0.0.dist-info/METADATA
azure_mgmt_hardwaresecuritymodules-1.0.0.dist-info/WHEEL
azure_mgmt_hardwaresecuritymodules-1.0.0.dist-info/top_level.txt
azure_mgmt_hardwaresecuritymodules-1.0.0.dist-info/RECORD
